[
{ "model": "public.county", "fields": {"name" : "Derry", "province" : "ulster", "towns" : [ "Aghadowey", "Ardgarvan", "Ardmore", "Articlave", "Artikelly", "Ballerin", "Ballykelly", "Ballymaguigan", "Ballyrashane", "Ballyronan", "Ballyrory", "Ballyscullion", "Banagher", "Bellaghy", "Bellarena", "Burnfoot", "Carrowclare", "Castledawson", "Castlerock", "Clady", "Claudy", "Coleraine", "Cranford", "Culmore", "Culnady", "Curran", "Derry City", "Derrynaflaw", "Desertmartin", "Downhill", "Draperstown", "Drummullan", "Drumraighland", "Drumsurn", "Dungiven", "Eglinton", "Feeny", "Foreglen", "Garvagh", "Glack", "Glenone", "Gortnahey", "Goshedan", "Greysteel", "Gulladuff", "Inishrush", "Killaloo", "Killywool", "Kilrea", "Knockcloghrim", "Largy", "Lettershendoney", "Limavady", "Loup", "Macosquin", "Maghera", "Magherafelt", "Maydown", "Moneymore", "Moneyneany", "Newbuildings", "Nixon's Corner", "Park", "Portrush", "Portstewart", "Ringsend", "Shanvey", "Straidarran", "Strathfoyle", "Straw", "Swatragh", "Tamlaght", "Tobermore", "Upperlands" ] }},
{ "model": "public.county", "fields": {"name" : "Kildare", "province" : "leinster", "towns" : [ "Allenwood", "Athy Town", "Ballitore", "Ballymore Eustace", "Ballyoulster", "Ballyroe", "Ballysax", "Brownstown", "Carragh", "Castledermot", "Celbridge", "Clane", "Coill Dubh (or Blackwood)", "Derrinturn", "Droichead Nua (formerly Newbridge)", "Grangemore", "Johnstown", "Kilberry", "Kilcock", "Kilcullen", "Kildare", "Kill", "Kilmeage", "Ladytown", "Leixlip", "Maddenstown", "Maynooth", "Milltown", "Monasterevin", "Naas Town", "Nurney", "Prosperous", "Rathangan", "Robertstown", "Sallins", "Straffan", "Suncroft" ] }},
{ "model": "public.county", "fields": {"name" : "Wexford", "province" : "leinster", "towns" : [ "Adamstown", "Ballycanew", "Ballycullane", "Ballygeary(or Rosslare Harbour)", "Ballyhack", "Ballysimon", "Barntown", "Bridgetown", "Bunclody-Carrickduff", "Camolin", "Campile", "Castle Ellis", "Castlebridge", "Clonegal", "Clongeen", "Clonroche", "Coolgreany", "Courtown Harbour", "Danescastle", "Duncannon", "Duncormick", "Enniscorthy Town", "Ferns", "Fethard-on-Sea", "Ford", "Gorey", "Grahormac", "Kilmore Quay", "Kilrane", "Murntown", "New Ross", "Newbawn", "Oilgate", "Piercetown", "Rosslare", "Taghmon", "Wexford Town" ] }},
{ "model": "public.county", "fields": {"name" : "Waterford", "province" : "munster", "towns" : [ "Abbeyside", "Aglish", "Ardmore", "Ballinroad", "Cappoquin", "Cheekpoint", "Clashmore", "Dungarvan Town", "Dunmore East", "Kill", "Kilmacthomas", "Lemybrien", "Lismore", "Passage East", "Portlaw", "Ring", "Stradbally", "Tallow", "Tramore Environs", "Tramore", "Villierstown", "Waterford City" ] }},
{ "model": "public.county", "fields": {"name" : "Longford", "province" : "leinster", "towns" : [ "Ballymahon", "Drumlish", "Granard", "Keenagh", "Lanesborough-Ballyleague", "Longford Town", "Meathas Truim(orEdgeworthstown)", "Newtownforbes" ] }},
{ "model": "public.county", "fields": {"name" : "Limerick", "province" : "munster", "towns" : [ "Abbeyfeale", "Adare", "Annacotty", "Ardagh", "Askeaton", "Athea", "Ballingarry", "Ballyagran", "Ballylanders", "Broadford", "Bruff", "Bruree", "Caherconlish", "Cappamore", "Carrigkerry", "Castleconnell", "Coonagh", "Croom", "Doon", "Dromcolliher", "Foynes", "Galbally", "Glen", "Glin", "Hospital", "Kilfinane", "Kilmallock", "Knocklong", "Limerick City", "Moroe", "Mountcollins", "Mungret", "Newcastle West", "O'Briensbridge-Montpelier", "Oola", "Pallas Green", "Pallaskenry", "Patrickswell", "Rathkeale", "Shanagolden" ] }},
{ "model": "public.county", "fields": {"name" : "Kilkenny", "province" : "leinster", "towns" : [ "Ballyragget", "Bennettsbridge", "Callan", "Castlecomer-Donaguile", "Clogh-Chatsworth", "Freshford", "Goresbridge", "Gowran", "Graiguenamanagh-Tinnahinch", "Inistioge", "Johnstown", "Kells", "Kilkenny", "Kilmacow", "Kilmoganny", "Lawcus", "Moneenroe", "Mooncoin", "Mullinavat", "Paulstown", "Piltown", "Slieverue", "Thomastown", "Urlingford" ] }},
{ "model": "public.county", "fields": {"name" : "Clare", "province" : "munster", "towns" : [ "Ardnacrusha (Castlebank)", "Ardskeagh", "Ballycannan", "Ballymulcashel", "Ballyvaughan", "Clonlara", "Corofin", "Cratloe", "Doonbeg", "Ennis Town", "Ennistymon", "Feakle", "Kildysart", "Kilfenora", "Kilkee", "Kilkishen", "Killaloe", "Kilmihill", "Kilrush Town", "Lahinch", "Liscannor", "Lisdoonvarna", "Milltown Malbay", "Newmarket-on-Fergus", "O'Briensbridge-Montpelier", "Quilty", "Quin", "Scarriff", "Shannon Environs", "Shannon", "Sixmilebridge", "Tulla", "Whitegate" ] }},
{ "model": "public.county", "fields": {"name" : "Leitrim", "province" : "connacht", "towns" : [ "Ballinamore", "Carrick-on-Shannon", "Carrigallen", "Dromahair", "Drumkeeran", "Drumshanbo", "Drumsna", "Kinlough", "Manorhamilton", "Mohill", "Roosky" ] }},
{ "model": "public.county", "fields": {"name" : "Roscommon", "province" : "connacht", "towns" : [ "Ballaghaderreen", "Ballinlough", "Ballyfarnon", "Boyle", "Carrick-on-Shannon", "Castlerea", "Clontuskert", "Elphin", "Frenchpark", "Keadew", "Lanesborough-Ballyleague", "Loughglinn", "Roosky", "Roscommon", "Strokestown" ] }},
{ "model": "public.county", "fields": {"name" : "Dublin", "province" : "leinster", "towns" : [ "Balbriggan", "Ballyboghil", "Brittas", "Donabate", "Dublin City", "Garristown", "Glencullen", "Kinsealy-Drinan", "Loughshinny", "Lusk", "Malahide", "Naul", "Newcastle", "Oldtown", "Portmarnock", "Portrane", "Rathcoole", "Rivermeade", "Rush", "Saggart", "Skerries", "Swords" ] }},
{ "model": "public.county", "fields": {"name" : "Sligo", "province" : "connacht", "towns" : [ "Ballincar", "Ballisodare", "Ballymote", "Charlestown-Bellahy", "Cliffoney", "Collooney", "Coolaney", "Easky", "Grange", "Gurteen", "Inniscrone", "Mullaghmore", "Riverstown", "Rosses Point", "Sligo", "Strandhill", "Tubbercurry" ] }},
{ "model": "public.county", "fields": {"name" : "Meath", "province" : "leinster", "towns" : [ "Ashbourne", "Athboy", "Ballivor", "Balreask", "Ceannanus Mór (formerly Kells) Town", "Clonard", "Clonee Village", "Donore", "Drumconrath", "Duleek", "Dunboyne", "Dunshaughlin", "Enfield", "Gormanston", "Julianstown/Whitecross", "Kentstown", "Kilcloon", "Kildalkey", "Kilmainham", "Kilmessan", "Laytown-Bettystown-Mornington", "Longwood", "Navan (An Uaimh) Town", "Nobber", "Oldcastle", "Rathmolyon", "Ratoath", "Slane", "Stamullen", "Summerhill", "Trim Town" ] }},
{ "model": "public.county", "fields": {"name" : "Monaghan", "province" : "ulster", "towns" : [ "Ballybay Environs", "Ballybay", "Bellanode", "Cabragh", "Carrickmacross Town", "Castleblayney Town", "Clones Town", "Emyvale", "Glasslough", "Inniskeen", "Monaghan Town", "Newbliss", "Rockcorry", "Scotstown", "Smithborough" ] }},
{ "model": "public.county", "fields": {"name" : "Louth", "province" : "leinster", "towns" : [ "Ardee", "Baltray", "Carlingford", "Castlebellingham/Kilsaran", "Clogherhead", "Collon", "Drogheda", "Dromiskin", "Dundalk Town", "Dunleer", "Jenkinstown", "Knockbridge", "Louth", "Omeath", "Tallanstown", "Termonfeckin", "Tinure", "Tullyallen" ] }},
{ "model": "public.county", "fields": {"name" : "Kerry", "province" : "munster", "towns" : [ "Abbeydorney", "Annascaul", "Ardfert", "Ballybunion", "Ballyduff", "Ballyheigue", "Ballylongford", "Beaufort", "Brosna", "Cahersiveen", "Castlegregory", "Castleisland", "Causeway", "Cromane", "Dingle", "Fenit", "Glenbeigh", "Gneevgullia", "Kenmare", "Kilgarvan", "Killarney Town", "Killorglin", "Knightstown", "Listowel Town", "Lixnaw", "Milltown", "Newtownsandes", "Rathmore", "Sneem", "Spa", "Tarbert", "Tralee Town", "Waterville-Spunkane" ] }},
{ "model": "public.county", "fields": {"name" : "Tipperary", "province" : "munster", "towns" : [ "Ardfinnan", "Ballina", "Ballingarry", "Ballyclerahan", "Ballyporeen", "Bansha", "Borrisokane", "Borrisoleigh", "Cahir", "Cappawhite", "Carrick-on-Suir Town", "Cashel Town", "Clogheen", "Clonmel", "Cloughjordan", "Dundrum", "Emly", "Fethard", "Golden", "Gortnahoo", "Holycross", "Killenaule", "Kilsheelan", "Littleton", "Mullinahone", "Nenagh Town", "Newcastle", "Newport", "Portroe", "Puckaun", "Reardnogy", "Roscrea", "Silvermines", "Templemore Town", "Templetuohy", "Thurles Town", "Tipperary Town", "Toomevara", "Two-Mile Borris" ] }},
{ "model": "public.county", "fields": {"name" : "Galway", "province" : "connacht", "towns" : [ "Ahascragh", "Athenry", "Ballinasloe Town", "Ballygar", "Carraroe", "Claregalway", "Clarinbridge", "Clifden", "Cloonboo", "Cong", "Craughwell", "Dunmore", "Eyrecourt", "Furbogh", "Galway City", "Glenamaddy", "Gort", "Headford", "Killimor", "Kilronan", "Kinvara", "Lackaghbeg", "Loughrea", "Monivea", "Mount Bellew", "Moycullen", "Moylough", "Oranmore", "Oughterard", "Portumna", "Roundstone", "Spiddle", "Tuam", "Woodford" ] }},
{ "model": "public.county", "fields": {"name" : "Mayo", "province" : "connacht", "towns" : [ "Achill Sound", "Balla", "Ballina", "Ballindine", "Ballinrobe", "Ballycastle", "Ballyhaunis", "Bangor Erris", "Belmullet", "Castlebar Town", "Charlestown-Bellahy", "Claremorris", "Cong", "Crossmolina", "Foxford", "Keel-Dooagh", "Kilkelly", "Killala", "Kilmaine", "Kiltimagh", "Knock", "Louisburgh", "Newport", "Shrule", "Swinford", "Westport" ] }},
{ "model": "public.county", "fields": {"name" : "Fermanagh", "province" : "ulster", "towns" : [ "Aghadrumsee", "Arney", "Ballinamallard", "Ballycassidy", "Belcoo", "Bellanaleck", "Belleek", "Blaney", "Boho", "Brookeborough", "Carrybridge", "Clabby", "Derrygonnelly", "Derrylin", "Derryvore", "Donagh", "Drumlaghy", "Ederney", "Enniskillen", "Florencecourt", "Garrison", "Holywell", "Irvinestown", "Kesh", "Killadeas", "Kinawley", "Lack", "Letterbreen", "Lisbellaw", "Lisnarick", "Lisnaskea", "Macken", "Magheraveely", "Maguiresbridge", "Monea", "Newtownbutler", "Rosslea", "Skea", "Springfield", "Tamlaght", "Teemore", "Tempo", "Trory", "Tullyhommon" ] }},
{ "model": "public.county", "fields": {"name" : "Offaly", "province" : "leinster", "towns" : [ "Ballycumber", "Banagher", "Belmont", "Birr", "Bracknagh", "Clara", "Cloghan", "Clonbullogue", "Coolagary", "Daingean", "Edenderry", "Ferbane", "Geashill", "Kilcormac (or Frankford)", "Killeigh", "Kinnitty", "Moneygall", "Mucklagh", "Portarlington", "Rhode", "Shannonbridge", "Shinrone", "Tullamore Town" ] }},
{ "model": "public.county", "fields": {"name" : "Armagh", "province" : "ulster", "towns" : [ "Aghacommon", "Annaghmore", "Annahugh", "Armagh City", "Ballymacnab", "Bannfoot", "Belleeks", "Bessbrook", "Blackwatertown", "Broomhill", "Camlough", "Carrickaness", "Charlemont", "Cladymore", "Clonmore", "Collegeland", "Corrinshego", "Craigavon", "Creggan", "Crossmaglen", "Cullaville", "Cullyhanna", "Darkley", "Derryhale", "Derrymacash", "Derrynoose", "Derrytrasna", "Dollingstown", "Dorsey", "Dromintee", "Drumnacanvy", "Edenaveys", "Forkill", "Hamiltonsbawn", "Jerrettspass", "Jonesborough", "Keady", "Killeen", "Killylea", "Kilmore", "Laurelvale", "Lislea", "Lisnadill", "Loughgall", "Loughgilly", "Lurgan", "Madden", "Maghery", "Markethill", "Meigh", "Middletown", "Milford", "Mountnorris", "Mullaghbawn", "Mullaghbrack", "Mullaghglass", "Newry", "Newtowncloghoge", "Newtownhamilton", "Portadown", "Poyntzpass", "Richhill", "Scotch Street", "Silverbridge", "Tandragee", "Tartaraghan", "The Birches", "Tynan", "Whitecross" ] }},
{ "model": "public.county", "fields": {"name" : "Donegal", "province" : "ulster", "towns" : [ "Annagry", "Ardara", "Ballintra", "Ballybofey-Stranorlar", "Ballyliffin", "Ballyshannon", "Bridge End", "Brinlack", "Bunbeg-Derrybeg", "Buncrana Town", "Bundoran Town", "Burnfoot", "Burtonport", "Carndonagh", "Carrick", "Carrigans", "Carrowkeel", "Castlefin", "Clonmany", "Convoy", "Creeslough", "Crocknamurleog", "Culdaff", "Donegal", "Dunfanaghy", "Dungloe", "Dunkineely", "Fahan", "Falcarragh (or Cross Roads)", "Glencolumbkille", "Glenties", "Gortahork", "Greencastle", "Kilcar", "Kildrum", "Killybegs", "Killygordan", "Kilmacrennan", "Laghy (Laghey)", "Letterkenny Town", "Lifford", "Loughanure", "Manorcunningham", "Meenlaragh", "Milford", "Mountcharles", "Moville", "Muff", "Newtowncunningham", "Pettigo", "Ramelton", "Rannafast", "Raphoe", "Rathmullan", "St. Johnston", "Tievebane" ] }},
{ "model": "public.county", "fields": {"name" : "Cork", "province" : "munster", "towns" : [ "Aghada-Farsid-Rostellan", "Ballineen and Enniskean", "Ballingeary", "Ballyclogh", "Ballycotton", "Ballydehob", "Ballydesmond", "Ballyhooly", "Ballymakeery", "Baltimore", "Bandon", "Banteer", "Bantry", "Blarney", "Boherbue", "Bridebridge", "Buttevant", "Carrigaline", "Carrigtwohill", "Castlelyons", "Castlemartyr", "Castletownbere", "Castletownroche", "Castletownshend", "Churchbay", "Clonakilty Town", "Cloyne", "Coachford", "Cobh Town", "Conna", "Cork City", "Courtmacsherry", "Crookstown", "Crosshaven", "Doneraile", "Drimoleague", "Dromina", "Drommahane", "Dunmanway", "Durrus", "Farran", "Fermoy Town", "Fountainstown", "Glanworth", "Inchigeelagh", "Innishannon", "Kanturk", "Kildorrery", "Killavullen", "Killeagh", "Killumney", "Kilworth", "Kinsale Town", "Knockglass", "Knocknagree", "Leap", "Liscarroll", "Macroom Town", "Mallow Town", "Midleton Town", "Milford", "Millstreet", "Mitchelstown", "Model Village (or Dripsey)", "Newmarket", "Newtown", "Passage West", "Rathard", "Rathcormac", "Rathluirc (or Charleville)", "Ringaskiddy (or Loughbeg)", "Rosscarbery", "Schull", "Shanagarry", "Skibbereen Town", "Timoleague", "Tower", "Union Hall", "Watergrasshill", "Whitegate", "Youghal" ] }},
{ "model": "public.county", "fields": {"name" : "Wicklow", "province" : "leinster", "towns" : [ "Arklow Town", "Ashford", "Aughrim", "Avoca", "Baltinglass", "Blessington", "Bray", "Carnew", "Donard", "Dunlavin", "Enniskerry", "Glenealy", "Greystones", "Kilcoole", "Kilmacanogue", "Kilpedder", "Laragh", "Newcastle", "Newtownmountkennedy", "Rathdrum", "Rathnew", "Roundwood", "Shillelagh", "Stratford-on-Slaney", "Tinahely", "Wicklow Town" ] }},
{ "model": "public.county", "fields": {"name" : "Tyrone", "province" : "ulster", "towns" : [ "Altamuskin", "Altishane", "Altmore", "Ardboe", "Ardstraw", "Artigarvan", "Augher", "Aughnacloy", "Ballygawley", "Ballymagorry", "Benburb", "Beragh", "Brackaville", "Bready", "Brockagh", "Caledon", "Campsie", "Cappagh", "Carnteel", "Carrickmore", "Castlecaulfield", "Castlederg", "Clady", "Clanabogan", "Clogher", "Clonoe", "Coagh", "Coalisland", "Cookstown", "Cranagh", "Derrycrin", "Donaghey", "Donaghmore", "Dooish", "Douglas Bridge", "Dromore", "Drumnakilly", "Drumquin", "Dungannon", "Dunnamanagh", "Dunnamore", "Edenderry", "Eglish", "Erganagh", "Eskra", "Fintona", "Fivemiletown", "Galbally", "Garvaghey", "Garvetagh", "Gillygooly", "Glebe", "Glencull", "Glenmornan", "Gortaclare", "Gortin", "Granville", "Greencastle", "Kildress", "Killay", "Killen", "Killeter", "Killyman", "Kilskeery", "Knockmoyle", "Landahaussy", "Loughmacrory", "Magheramason", "Moortown", "Mountfield", "Mountjoy", "Moy", "Moygashel", "Newmills", "Newtownstewart", "Omagh", "Plumbridge", "Pomeroy", "Rock", "Rousky", "Sandholes", "Seskinore", "Shanmaghery", "Sion Mills", "Sixmilecross", "Spamount", "Stewartstown", "Strabane", "Tamnamore", "Trillick", "Tullyhogue", "Tullywiggan", "Victoria Bridge", "Washing Bay", "Whitehouse" ] }},
{ "model": "public.county", "fields": {"name" : "Cavan", "province" : "ulster", "towns" : [ "Arvagh", "Bailieborough", "Ballinagh", "Ballyconnell", "Ballyhaise", "Ballyjamesduff", "Belturbet", "Blacklion", "Butlersbridge", "Cavan Town", "Cootehill", "Killeshandra", "Kilnaleck", "Kingscourt", "Mullagh", "Shercock", "Swanlinbar", "Virginia" ] }},
{ "model": "public.county", "fields": {"name" : "Down", "province" : "ulster", "towns" : [ "Annaclone", "Annahilt", "Annalong", "Annsborough", "Ardglass", "Atticall", "Ballela", "Balloo", "Ballygowan", "Ballyhalbert", "Ballyhornan", "Ballykinler", "Ballylesson", "Ballymacmaine", "Ballynahinch", "Ballyskeagh", "Ballywalter", "Banbridge", "Bangor", "Belfast", "Blackskull", "Bleary", "Bryansford", "Burren", "Carrowdore", "Carryduff", "Castlewellan", "Cloghy", "Clough", "Cloughoge", "Comber", "Conlig", "Corbet", "Crawfordsburn", "Crossgar", "Donaghadee", "Donaghcloney", "Downpatrick", "Dromara", "Dromore", "Drumaness", "Drumbeg", "Drumbo", "Drumlough/Hillsborough", "Drumlough/Rathfriland", "Dundonald", "Dundrum", "Dunnaval", "Edenderry", "Gamblestown", "Gibson's Hill", "Gilford", "Greyabbey", "Groomsport", "Helen's Bay", "Hillhall", "Hillsborough", "Hilltown", "Holywood", "Katesbridge", "Kilcoo", "Kilkeel", "Killinchy", "Killough", "Killowen", "Killyleagh", "Kilmore", "Kinallen", "Kircubbin", "Lawrencetown", "Leitrim", "Listooder", "Loughbrickland", "Loughinisland", "Lurganare", "Lurganville", "Magheraconluce", "Magheralin", "Mayobridge", "Mazetown", "Millisle", "Moira", "Moneyreagh", "Moneyslane", "Monteith", "Newcastle", "Newry", "Newtownards", "Portaferry", "Portavogie", "Rathfriland", "Ravernet", "Rostrevor", "Saintfield", "Scarva", "Seaforde", "Sheeptown", "Shrigley", "Spa", "Strangford", "Tullylish", "Waringsford", "Waringstown", "Warrenpoint", "Whiterock" ] }},
{ "model": "public.county", "fields": {"name" : "Carlow", "province" : "leinster", "towns" : [ "Ballon", "Borris", "Bunclody-Carrickduff", "Carlow Town", "Clonegal", "Graiguenamanagh-Tinnahinch", "Hacketstown", "Kernanstown", "Leighlinbridge", "Muinebeag (formerly Bagenalstown)", "Rathvilly", "Tinriland", "Tullow" ] }},
{ "model": "public.county", "fields": {"name" : "Laois", "province" : "leinster", "towns" : [ "Abbeyleix", "Ballinakill", "Ballylinan", "Ballyroan", "Borris-in-Ossory", "Castletown", "Clonaslee", "Durrow", "Emo", "Mountmellick", "Mountrath", "Newtown", "Portarlington", "Portlaoise(formerlyMaryborough)", "Rathdowney", "Stradbally" ] }},
{ "model": "public.county", "fields": {"name" : "Antrim", "province" : "ulster", "towns" : [ "Aghagallon", "Aghalee", "Ahoghill", "Aldergrove", "Antrim Town", "Armoy", "Aughafatten", "Ballintoy", "Ballybogy", "Ballycarry", "Ballycastle", "Ballyclare", "Ballyeaston", "Ballygalley", "Ballylinney", "Ballymartin", "Ballymena", "Ballymoney", "Ballynure", "Ballyrobert", "Ballystrudder", "Ballyvoy", "Balnamore", "Belfast", "Bendooragh", "Broughshane", "Buckna", "Bushmills", "Capecastle", "Cargan", "Carnalbanagh", "Carncastle", "Carnlough", "Carrickfergus", "Clogh", "Cloughmills", "Cogry-Kilbride", "Corkey", "Craigarogan", "Creagh", "Crumlin", "Cullybackey", "Cushendall", "Cushendun", "Derrykeighan", "Derrymore", "Dervock", "Doagh", "Donegore", "Drinns Bay", "Dunadry", "Dundrod", "Dunloy", "Dunmurry", "Dunseverick", "Finvoy", "Gawley's Gate", "Glenarm", "Glenavy", "Glengormley", "Glenoe", "Glynn", "Gracehill", "Grange Corner", "Greenisland", "Groggan", "Halfpenny Gate", "Islandmagee", "Jordanstown", "Kells-Connor", "Kellswater", "Keshbridge", "Killead", "Knocknacarry", "Lambeg", "Larne", "Loughguile", "Lower Ballinderry", "Lurganure", "Maghaberry", "Magheramorne", "Mallusk", "Martinstown", "Mill Bay", "Millbank", "Milltown", "Moneyglass", "Moss-Side", "Mounthill", "Mullaghboy", "Newtown Crommelin", "Newtownabbey", "Parkgate", "Portballintrae", "Portbraddon", "Portglenone", "Randalstown", "Rasharkin", "Roughfort", "Stoneyford", "Straid", "Stranocum", "Templepatrick", "Toome", "Tullynacross", "Upper Ballinderry", "Waterfoot", "Whitehead", "Whitehouse" ] }},
{ "model": "public.county", "fields": {"name" : "Westmeath", "province" : "leinster", "towns" : [ "Athlone Town", "Ballymore", "Ballynacargy", "Castlepollard", "Clonmellon", "Collinstown", "Delvin", "Glassan", "Kilbeggan", "Killucan-Rathwire", "Kinnegad", "Moate", "Mullingar", "Multyfarnham", "Raharney", "Rochfortbridge", "Tyrrellspass" ] }}
]
